Workbook
Name lista_tipos: Apoio!$A$2:$A$6
Name lista_categorias: Apoio!$B$2:$B$6
Name lista_parentesco: Apoio!$C$2:$C$4
Name tipo_informes: Informes!$E$8:$E$107
Name valor_informes: Informes!$F$8:$F$107
Name irrf_informes: Informes!$G$8:$G$107
Name cat_notas: Notas!$E$8:$E$107
Name valor_notas: Notas!$F$8:$F$107

Sheet Menu
B2: Imposto de Renda
B3: Controle dos dados para a declaração (dados de exemplo)
B5: =HYPERLINK("#'Titular'!A1","Titular") | E5: =HYPERLINK("#'Informes'!A1","Informes")
B7: Dados pessoais e dependentes | E7: Rendimentos e imposto retido
B10: =HYPERLINK("#'Notas'!A1","Notas") | E10: =HYPERLINK("#'Resumo'!A1","Resumo")
B12: Despesas dedutíveis | E12: Totais e gráficos
B15: Links rápidos
B16: Receita Federal: Meu Imposto de Renda
B17: Portal gov.br
B20: Células brancas: você preenche. Células azuladas: calculadas, protegidas.

Sheet Titular
B2: Titular
B3: Quem declara e quem depende de você
B4: =HYPERLINK("#'Menu'!A1","Menu") | C4: =HYPERLINK("#'Titular'!A1","Titular") | D4: =HYPERLINK("#'Informes'!A1","Informes") | E4: =HYPERLINK("#'Notas'!A1","Notas") | F4: =HYPERLINK("#'Resumo'!A1","Resumo")
B6: Campo | C6: Informação
B7: Nome completo | C7: Maria Exemplo da Silva
B8: CPF | C8: 12345678909
B9: Data de nascimento | C9: 33010
B10: E-mail | C10: maria.exemplo@email.com
B11: Ano-calendário | C11: 2025
B14: Dependente | C14: CPF | D14: Parentesco
B15: João Exemplo | C15: 98765432100 | D15: Filho(a)
B19: Nº de dependentes | C19: =COUNTA(B15:B17)

Sheet Informes
B2: Informes de rendimentos
B3: De onde veio o dinheiro e quanto já foi retido na fonte
B4: =HYPERLINK("#'Menu'!A1","Menu") | C4: =HYPERLINK("#'Titular'!A1","Titular") | D4: =HYPERLINK("#'Informes'!A1","Informes") | E4: =HYPERLINK("#'Notas'!A1","Notas") | F4: =HYPERLINK("#'Resumo'!A1","Resumo")
B5: Lançamentos | C5: =COUNTA(B8:B107) | E5: Total (R$) | F5: =SUM(F8:F107) | G5: =SUM(G8:G107)
B7: Fonte pagadora | C7: CNPJ | D7: Data | E7: Tipo | F7: Valor (R$) | G7: IRRF (R$) | H7: Status
B8: Empresa Exemplo Ltda | C8: 11222333000181 | D8: 46022 | E8: Salário | F8: 60000 | G8: 4200 | H8: =IF(B8="","",IF(OR(E8="",F8="",D8=""),"Incompleto","OK"))
B9: Imobiliária Exemplo | C9: 44555666000199 | D9: 46022 | E9: Aluguel | F9: 18000 | G9: 0 | H9: =IF(B9="","",IF(OR(E9="",F9="",D9=""),"Incompleto","OK"))
B10: Banco Exemplo S.A. | C10: 77888999000122 | D10: 46022 | E10: Outros | F10: 1200 | G10: 0 | H10: =IF(B10="","",IF(OR(E10="",F10="",D10=""),"Incompleto","OK"))
H11: =IF(B11="","",IF(OR(E11="",F11="",D11=""),"Incompleto","OK"))
H12: =IF(B12="","",IF(OR(E12="",F12="",D12=""),"Incompleto","OK"))
H13: =IF(B13="","",IF(OR(E13="",F13="",D13=""),"Incompleto","OK"))
H14: =IF(B14="","",IF(OR(E14="",F14="",D14=""),"Incompleto","OK"))
H15: =IF(B15="","",IF(OR(E15="",F15="",D15=""),"Incompleto","OK"))
H16: =IF(B16="","",IF(OR(E16="",F16="",D16=""),"Incompleto","OK"))
H17: =IF(B17="","",IF(OR(E17="",F17="",D17=""),"Incompleto","OK"))
H18: =IF(B18="","",IF(OR(E18="",F18="",D18=""),"Incompleto","OK"))
H19: =IF(B19="","",IF(OR(E19="",F19="",D19=""),"Incompleto","OK"))
H20: =IF(B20="","",IF(OR(E20="",F20="",D20=""),"Incompleto","OK"))
H21: =IF(B21="","",IF(OR(E21="",F21="",D21=""),"Incompleto","OK"))
H22: =IF(B22="","",IF(OR(E22="",F22="",D22=""),"Incompleto","OK"))
... H107: =IF(B107="","",IF(OR(E107="",F107="",D107=""),"Incompleto","OK"))

Sheet Notas
B2: Notas e despesas
B3: Gastos que podem entrar como dedução
B4: =HYPERLINK("#'Menu'!A1","Menu") | C4: =HYPERLINK("#'Titular'!A1","Titular") | D4: =HYPERLINK("#'Informes'!A1","Informes") | E4: =HYPERLINK("#'Notas'!A1","Notas") | F4: =HYPERLINK("#'Resumo'!A1","Resumo")
B5: Lançamentos | C5: =COUNTA(B8:B107) | E5: Total (R$) | F5: =SUM(F8:F107)
B7: Prestador | C7: CNPJ/CPF | D7: Data | E7: Categoria | F7: Valor (R$) | H7: Status
B8: Clínica Exemplo | C8: 12345678000195 | D8: 45726 | E8: Saúde | F8: 1800 | H8: =IF(B8="","",IF(OR(E8="",F8="",D8=""),"Incompleto","OK"))
B9: Escola Exemplo | C9: 98765432000110 | D9: 45693 | E9: Educação | F9: 3500 | H9: =IF(B9="","",IF(OR(E9="",F9="",D9=""),"Incompleto","OK"))
B10: Plano de Saúde Exemplo | C10: 55443322000166 | D10: 45809 | E10: Saúde | F10: 4200 | H10: =IF(B10="","",IF(OR(E10="",F10="",D10=""),"Incompleto","OK"))
H11: =IF(B11="","",IF(OR(E11="",F11="",D11=""),"Incompleto","OK"))
H12: =IF(B12="","",IF(OR(E12="",F12="",D12=""),"Incompleto","OK"))
H13: =IF(B13="","",IF(OR(E13="",F13="",D13=""),"Incompleto","OK"))
H14: =IF(B14="","",IF(OR(E14="",F14="",D14=""),"Incompleto","OK"))
H15: =IF(B15="","",IF(OR(E15="",F15="",D15=""),"Incompleto","OK"))
H16: =IF(B16="","",IF(OR(E16="",F16="",D16=""),"Incompleto","OK"))
H17: =IF(B17="","",IF(OR(E17="",F17="",D17=""),"Incompleto","OK"))
H18: =IF(B18="","",IF(OR(E18="",F18="",D18=""),"Incompleto","OK"))
H19: =IF(B19="","",IF(OR(E19="",F19="",D19=""),"Incompleto","OK"))
H20: =IF(B20="","",IF(OR(E20="",F20="",D20=""),"Incompleto","OK"))
H21: =IF(B21="","",IF(OR(E21="",F21="",D21=""),"Incompleto","OK"))
H22: =IF(B22="","",IF(OR(E22="",F22="",D22=""),"Incompleto","OK"))
... H107: =IF(B107="","",IF(OR(E107="",F107="",D107=""),"Incompleto","OK"))

Sheet Resumo
B2: Resumo
B3: Tudo somado a partir das abas Informes e Notas
B4: =HYPERLINK("#'Menu'!A1","Menu") | C4: =HYPERLINK("#'Titular'!A1","Titular") | D4: =HYPERLINK("#'Informes'!A1","Informes") | E4: =HYPERLINK("#'Notas'!A1","Notas") | F4: =HYPERLINK("#'Resumo'!A1","Resumo")
B6: Total de rendimentos | E6: Imposto retido (IRRF)
B7: =SUM(C10:C14) | E7: =SUM(irrf_informes)
B9: Rendimentos por tipo | C9: Total (R$)
B10: =Apoio!A2 | C10: =SUMIF(tipo_informes,B10,valor_informes)
B11: =Apoio!A3 | C11: =SUMIF(tipo_informes,B11,valor_informes)
B12: =Apoio!A4 | C12: =SUMIF(tipo_informes,B12,valor_informes)
B13: =Apoio!A5 | C13: =SUMIF(tipo_informes,B13,valor_informes)
B14: =Apoio!A6 | C14: =SUMIF(tipo_informes,B14,valor_informes)
B15: Total | C15: =SUM(C10:C14)
B17: Despesas por categoria | C17: Total (R$)
B18: =Apoio!B2 | C18: =SUMIF(cat_notas,B18,valor_notas)
B19: =Apoio!B3 | C19: =SUMIF(cat_notas,B19,valor_notas)
B20: =Apoio!B4 | C20: =SUMIF(cat_notas,B20,valor_notas)
B21: =Apoio!B5 | C21: =SUMIF(cat_notas,B21,valor_notas)
B22: =Apoio!B6 | C22: =SUMIF(cat_notas,B22,valor_notas)
B23: Total | C23: =SUM(C18:C22)
B25: Linhas incompletas | C25: =COUNTIF(Informes!H8:H107,"Incompleto")+COUNTIF(Notas!H8:H107,"Incompleto")

Sheet Apoio
A1: Tipo de rendimento | B1: Categoria de despesa | C1: Parentesco
A2: Salário | B2: Saúde | C2: Filho(a)
A3: Aluguel | B3: Educação | C3: Cônjuge
A4: Aposentadoria | B4: Previdência privada | C4: Outro
A5: Pró-labore | B5: Pensão alimentícia
A6: Outros | B6: Outras
